cis_checks_test_3/__init__.py
cis_checks_test_3/iam_control_1.py
cis_checks_test_3/logging_control_2.py
cis_checks_test_3/monitoring_control_3.py
cis_checks_test_3/networking_control_4.py
cis_checks_test_3/security_control_5.py
cis_checks_test_3/utils.py
cis_checks_test_3-0.0.7.dist-info/METADATA
cis_checks_test_3-0.0.7.dist-info/WHEEL
cis_checks_test_3-0.0.7.dist-info/top_level.txt
cis_checks_test_3-0.0.7.dist-info/RECORD
